{
	"credit": "Made with Blockbench",
	"render_type": "minecraft:cutout",
	"texture_size": [32, 32],
	"textures": {
		"1": "createcraftedbeginning:block/breeze_chamber/chilled_active"
	},
	"elements": [
		{
			"from": [4, 6, 4],
			"to": [12, 14, 12],
			"rotation": {"angle": 0, "axis": "y", "origin": [6, 6, 6]},
			"faces": {
				"north": {"uv": [4, 4, 8, 8], "texture": "#1"},
				"east": {"uv": [0, 4, 4, 8], "texture": "#1"},
				"south": {"uv": [12, 4, 16, 8], "texture": "#1"},
				"west": {"uv": [8, 4, 12, 8], "texture": "#1"},
				"up": {"uv": [4, 0, 8, 4], "texture": "#1"},
				"down": {"uv": [8, 0, 12, 4], "texture": "#1"}
			}
		},
		{
			"from": [3, 7, 3],
			"to": [13, 11, 7],
			"rotation": {"angle": 0, "axis": "y", "origin": [3, 8, 3]},
			"faces": {
				"north": {"uv": [3.5, 13.5, 8.5, 15.5], "texture": "#1"},
				"east": {"uv": [1.5, 13.5, 3.5, 15.5], "texture": "#1"},
				"west": {"uv": [8.5, 13.5, 10.5, 15.5], "texture": "#1"}
			}
		},
		{
			"from": [13, 7, 3],
			"to": [3, 11, 7],
			"rotation": {"angle": 0, "axis": "y", "origin": [13, 8, 3]},
			"faces": {
				"north": {"uv": [3.5, 13.5, 8.5, 15.5], "texture": "#1"},
				"east": {"uv": [1.5, 13.5, 3.5, 15.5], "texture": "#1"},
				"west": {"uv": [8.5, 13.5, 10.5, 15.5], "texture": "#1"}
			}
		}
	]
}